xtea3.py
xtea3-1.0.0.dist-info/METADATA
xtea3-1.0.0.dist-info/WHEEL
xtea3-1.0.0.dist-info/top_level.txt
xtea3-1.0.0.dist-info/zip-safe
xtea3-1.0.0.dist-info/RECORD
